{
  "default": {
    "voiceInfo": {
      "emotion": "good",
      "lang": "ru-RU",
      "speaker": "alena",
      "speed": 1.2
    },
    "types": {},
    "macros": {
      "i_will_call_back": {},
      "hello": {},
      "when_callback": {},
      "i_said": {},
      "sorry_wont_call": {},
      "i_will_wait": {},
      "i_can_hear_you": {},
      "dont_understand": {},
      "dont_understand_hangup": {},
      "yes_i_am_a_robot": {},
      "is_that_all": {},
      "greeting": {}
    },
    "phrases": {
      "i_will_call_back": [
        {
          "text": "Хорошо, я вам перезвоню!",
          "voiceInfo": {
            "speed": 1.2,
            "variation": 5
          }
        }
      ],
      "hello": {
        "random": [
          [
            {
              "text": "Алло"
            }
          ],
          [
            {
              "text": "Алло?"
            }
          ],
          [
            {
              "text": "Вы меня слышите?"
            }
          ]
        ]
      },
      "when_callback": [
        {
          "text": "Когда я могу перезвонить?"
        }
      ],
      "i_said": [
        {
          "text": "Я говорю"
        }
      ],
      "sorry_wont_call": [
        {
          "text": "Извините за беспокойство, всего доброго, до свидания!"
        }
      ],
      "i_will_wait": {
        "random": [
          [
            {
              "text": "Хорошо, я жду"
            }
          ],
          [
            {
              "text": "Конечно, я жду"
            }
          ],
          [
            {
              "text": "Хорошо, я подожду"
            }
          ]
        ]
      },
      "i_can_hear_you": [
        {
          "text": "Да. я вас слышу"
        }
      ],
      "dont_understand": {
        "random": [
          [
            {
              "text": "Извините, не расслышал, можете повторить"
            }
          ],
          [
            {
              "text": "Плохо слышно, повторите пожалуйста?"
            }
          ]
        ]
      },
      "dont_understand_hangup": [
        {
          "text": "я вас очень плохо слышно, я перезвоню вам позже, до свидания"
        }
      ],
      "yes_i_am_a_robot": [
        {
          "text": "Да, я робот, надеюсь, это не повлияет на наш дальнейший диалог"
        }
      ],
      "greeting": {
        "first": [
          {
            "text": "Здравствуйте, это модель на синтезе с загрузкой номеров телефонов из файла и выгрузкой результатов разговоров",
            "voiceInfo": {
              "speed": 1.2,
              "variation": 5
            }
          }
        ],
        "repeat": {
          "random": [
              {
                "text": "Это модель на синтезе с загрузкой номеров телефонов из файла и выгрузкой результатов разговоров"
              }
          ]
        }
      }
    }
  }
}